ptrcalc.py
ptrcalc-0.0.1.dist-info/METADATA
ptrcalc-0.0.1.dist-info/WHEEL
ptrcalc-0.0.1.dist-info/entry_points.txt
ptrcalc-0.0.1.dist-info/licenses/LICENSE
ptrcalc-0.0.1.dist-info/RECORD
