Metadata-Version: 2.3
Name: ptrcalc
Version: 0.0.1
Author-email: clerie <hallo@clerie.de>
License: GNU GENERAL PUBLIC LICENSE
License-File: LICENSE
Requires-Python: >=3.11
